setup.cfg
setup.py
diff/__init__.py
diff/tools/__init__.py
diff/tools/models.py
diff/tools/results.py
diff_tools.egg-info/PKG-INFO
diff_tools.egg-info/SOURCES.txt
diff_tools.egg-info/dependency_links.txt
diff_tools.egg-info/requires.txt
diff_tools.egg-info/top_level.txt
tests/__init__.py
tests/integration/__init__.py
tests/integration/test_e2e.py
tests/unit/__init__.py
tests/unit/conftest.py
tests/unit/test_models.py
tests/unit/test_results.py