Metadata-Version: 1.1
Name: diff-tools
Version: 0.0.1
Summary: A setup tools to diffing contents
Home-page: https://github.com/mcai4gl2/diff-tools
Author: Geng Li
Author-email: ligeng0420@gmail.com
License: MIT
Platform: UNKNOWN
Classifier: Programming Language :: Python :: 2.7
Classifier: Topic :: Database
Classifier: Topic :: Software Development :: Libraries
